magicapp_api/__init__
magicapp_api/api_calls.py
magicapp_api/api_wrapper.py
magicapp_api-0.0.10.dist-info/LICENSE
magicapp_api-0.0.10.dist-info/METADATA
magicapp_api-0.0.10.dist-info/WHEEL
magicapp_api-0.0.10.dist-info/RECORD
