Metadata-Version: 2.1
Name: magicapp-api
Version: 0.0.10
Summary: Wrapper for the Magic API
Author: Anders Vandvik
Author-email: anders@sanders.technology
Requires-Python: >=3.11,<3.12
Classifier: Development Status :: 3 - Alpha
Classifier: Intended Audience :: Developers
Classifier: License :: OSI Approved :: MIT License
Classifier: Operating System :: OS Independent
Classifier: Programming Language :: Python :: 3
Classifier: Programming Language :: Python :: 3.11
Requires-Dist: magicapp-common-assets (>=0.0.9,<0.0.10)
Requires-Dist: pytest (>=8.1.1,<9.0.0)
Requires-Dist: python-dotenv (>=1.0.1,<2.0.0)
Requires-Dist: requests (>=2.31.0,<3.0.0)
